{"choice":[{"t":"Внутренняя энергия тела — это:","o":["Кинетическая энергия тела","Энергия движения тела как целого","Потенциальная энергия высоты","Энергия движения и взаимодействия его частиц"],"a":3},{"t":"Температура тела связана со скоростью движения частиц так:","o":["Чем выше температура, тем медленнее частицы","Чем выше температура, тем быстрее движутся частицы","Частицы останавливаются при нагреве","Скорость частиц не зависит от температуры"],"a":1},{"t":"Какой вид теплопередачи происходит без переноса вещества и возможен в вакууме?","o":["Конвекция","Теплопроводность","Излучение","Кипение"],"a":2},{"t":"Конвекция — это перенос энергии:","o":["Лучами в вакууме","При трении","Потоками (струями) жидкости или газа","Через неподвижное твёрдое тело"],"a":2},{"t":"Удельная теплоёмкость показывает:","o":["Сколько теплоты нужно, чтобы нагреть 1 кг вещества на $1 ^{\\circ}C$","Температуру плавления","Сколько теплоты выделяет 1 кг топлива","Сколько теплоты при кипении"],"a":0},{"t":"При плавлении кристаллического тела температура:","o":["Не изменяется, пока тело плавится","Скачет","Растёт","Падает"],"a":0},{"t":"Испарение происходит:","o":["Только в вакууме","Только при кипении","Только в твёрдых телах","При любой температуре с поверхности жидкости"],"a":3},{"t":"Кипение происходит:","o":["При определённой температуре по всему объёму жидкости","При любой температуре","Только с поверхности","Без подвода теплоты"],"a":0},{"t":"Удельная теплота сгорания топлива показывает:","o":["Сколько теплоты при плавлении","Массу топлива","Температуру горения","Сколько теплоты выделяет 1 кг топлива при полном сгорании"],"a":3},{"t":"Два рода электрических зарядов:","o":["Положительный и отрицательный","Северный и южный","Большой и малый","Сильный и слабый"],"a":0},{"t":"Одноимённые заряды:","o":["Исчезают","Притягиваются","Не взаимодействуют","Отталкиваются"],"a":3},{"t":"Разноимённые заряды:","o":["Отталкиваются","Притягиваются","Складываются","Не взаимодействуют"],"a":1},{"t":"Электрический ток — это:","o":["Любое движение электронов","Нагрев проводника","Хаотичное движение молекул","Направленное движение заряженных частиц"],"a":3},{"t":"Сила тока измеряется:","o":["Амперметром, включённым последовательно","Омметром","Вольтметром параллельно","Барометром"],"a":0},{"t":"Напряжение измеряется:","o":["Динамометром","Термометром","Амперметром последовательно","Вольтметром, включённым параллельно"],"a":3},{"t":"Закон Ома для участка цепи:","o":["Сила тока равна напряжению","Напряжение равно работе","Сопротивление равно мощности","Сила тока прямо пропорциональна напряжению и обратно — сопротивлению"],"a":3},{"t":"При последовательном соединении проводников сила тока:","o":["Равна нулю","Складывается","Одинакова на всех участках","Делится поровну"],"a":2},{"t":"При параллельном соединении напряжение на ветвях:","o":["Делится","Равно нулю","Складывается","Одинаково на всех ветвях"],"a":3},{"t":"Закон Джоуля–Ленца описывает:","o":["Работу силы тяжести","Силу Архимеда","Количество теплоты при прохождении тока","Давление газа"],"a":2},{"t":"Причина короткого замыкания:","o":["Рост сопротивления","Снижение напряжения до нуля","Резкое уменьшение сопротивления и рост силы тока","Отключение источника"],"a":2},{"t":"Проводники — это вещества, которые:","o":["Притягивают магнит","Не проводят ток","Только нагреваются","Хорошо проводят электрический ток"],"a":3},{"t":"Опыт Эрстеда показал, что:","o":["Магнит создаёт ток","Ток не нагревает","Вокруг проводника с током есть магнитное поле","Заряды не движутся"],"a":2},{"t":"Одноимённые полюсы магнитов:","o":["Отталкиваются","Исчезают","Не взаимодействуют","Притягиваются"],"a":0},{"t":"Магнитное поле Земли защищает планету от:","o":["Ультрафиолета","Потоков заряженных частиц из космоса","Метеоритов","Землетрясений"],"a":1},{"t":"Электромагнит — это:","o":["Источник тока","Катушка с током и железным сердечником","Конденсатор","Постоянный магнит"],"a":1},{"t":"Явление электромагнитной индукции — это:","o":["Нагрев проводника током","Возникновение тока при изменении магнитного поля","Свечение лампы","Притяжение зарядов"],"a":1},{"t":"Что преобразует электродвигатель?","o":["Механическую в тепловую","Электрическую энергию в механическую","Свет в электричество","Тепло в свет"],"a":1},{"t":"Относительная влажность воздуха измеряется:","o":["Барометром","Динамометром","Амперметром","Гигрометром (психрометром)"],"a":3},{"t":"При теплообмене тёплое тело:","o":["Получает теплоту от холодного","Нагревается ещё сильнее","Отдаёт теплоту холодному до равновесия","Не обменивается теплом"],"a":2},{"t":"Уравнение теплового баланса означает, что:","o":["Теплота исчезает","Теплота возникает из ничего","Количество отданной теплоты равно полученной","Температуры всегда равны"],"a":2},{"t":"КПД теплового двигателя всегда:","o":["Больше 100 %","Равен 100 %","Меньше 100 %","Равен нулю"],"a":2},{"t":"Кристаллические тела отличаются от аморфных тем, что:","o":["Имеют определённую температуру плавления","Плавятся постепенно без точки плавления","Всегда прозрачны","Не плавятся"],"a":0},{"t":"Капиллярные явления — это:","o":["Намагничивание","Кипение жидкости","Электризация тел","Подъём/опускание жидкости в тонких трубках"],"a":3},{"t":"Элементарный электрический заряд — это заряд:","o":["Атома","Электрона (наименьший)","Тела","Молекулы"],"a":1},{"t":"Тепловое расширение тел при нагревании проявляется в том, что тела:","o":["Не меняются","Уменьшают объём","Увеличивают свой объём","Теряют массу"],"a":2},{"t":"Через проводник идёт ток 10 А в течение 5 с. Найдите прошедший заряд.","o":["100 Кл","10 Кл","50 Кл","5 Кл"],"a":2},{"t":"Мощность прибора 100 Вт, время работы 100 с. Найдите работу тока.","o":["5000 Дж","100 Дж","20000 Дж","10000 Дж"],"a":3},{"t":"Сколько теплоты нужно, чтобы расплавить 2 кг льда при температуре плавления ($\\lambda = 330000$ Дж/кг)?","o":["660000 Дж","330000 Дж","1320000 Дж","1980000 Дж"],"a":0},{"t":"Напряжение 24 В, сила тока 3 А. Найдите сопротивление.","o":["8 Ом","24 Ом","3 Ом","16 Ом"],"a":0},{"t":"Через проводник идёт ток 2 А в течение 20 с. Найдите прошедший заряд.","o":["2 Кл","20 Кл","40 Кл","80 Кл"],"a":2},{"t":"Сколько теплоты нужно, чтобы расплавить 3 кг льда при температуре плавления ($\\lambda = 330000$ Дж/кг)?","o":["990000 Дж","330000 Дж","495000 Дж","1980000 Дж"],"a":0},{"t":"Сколько теплоты нужно, чтобы расплавить 3 кг олова при температуре плавления ($\\lambda = 80000$ Дж/кг)?","o":["240000 Дж","480000 Дж","120000 Дж","80000 Дж"],"a":0},{"t":"Ток 2 А идёт через резистор 2 Ом в течение 5 с. Теплота (закон Джоуля–Ленца)?","o":["20 Дж","80 Дж","4 Дж","40 Дж"],"a":3},{"t":"Напряжение 12 В, сопротивление 6 Ом. Найдите силу тока (закон Ома).","o":["72 А","12 А","2 А","6 А"],"a":2},{"t":"Два резистора 3 Ом и 12 Ом соединены последовательно. Общее сопротивление?","o":["30 Ом","15 Ом","9 Ом","36 Ом"],"a":1},{"t":"Напряжение 220 В, сила тока 2 А. Найдите мощность тока.","o":["220 Вт","440 Вт","222 Вт","880 Вт"],"a":1},{"t":"Воду массой 1 кг нагрели от $20 ^{\\circ}C$ до $90 ^{\\circ}C (c = 4200)$. Сколько теплоты получено?","o":["588000 Дж","4200 Дж","294000 Дж","147000 Дж"],"a":2},{"t":"Сколько теплоты нужно для нагрева 3 кг алюминия ($c = 900$ Дж/(кг$\\cdot ^{\\circ}C$)) на $50 ^{\\circ}C$?","o":["45000 Дж","67500 Дж","270000 Дж","135000 Дж"],"a":3},{"t":"Сила тока 3 А, сопротивление 20 Ом. Найдите напряжение.","o":["120 В","23 В","3 В","60 В"],"a":3},{"t":"Напряжение 12 В, сила тока 3 А. Найдите сопротивление.","o":["8 Ом","12 Ом","4 Ом","3 Ом"],"a":2},{"t":"Сколько теплоты нужно для нагрева 1 кг воды ($c = 4200$ Дж/(кг$\\cdot ^{\\circ}C$)) на $10 ^{\\circ}C$?","o":["21000 Дж","4200 Дж","84000 Дж","42000 Дж"],"a":3},{"t":"Напряжение 12 В, сила тока 4 А. Найдите сопротивление.","o":["4 Ом","6 Ом","12 Ом","3 Ом"],"a":3},{"t":"Мощность прибора 40 Вт, время работы 10 с. Найдите работу тока.","o":["10 Дж","800 Дж","40 Дж","400 Дж"],"a":3},{"t":"Сила тока 3 А, сопротивление 5 Ом. Найдите напряжение.","o":["3 В","8 В","15 В","30 В"],"a":2},{"t":"Воду массой 2 кг нагрели от $30 ^{\\circ}C$ до $80 ^{\\circ}C (c = 4200)$. Сколько теплоты получено?","o":["420000 Дж","840000 Дж","210000 Дж","8400 Дж"],"a":0},{"t":"Напряжение 24 В, сила тока 2 А. Найдите сопротивление.","o":["24 Ом","2 Ом","48 Ом","12 Ом"],"a":3},{"t":"Сила тока 1 А, сопротивление 5 Ом. Найдите напряжение.","o":["1 В","5 В","10 В","6 В"],"a":1},{"t":"Сколько теплоты нужно для нагрева 0,5 кг воды ($c = 4200$ Дж/(кг$\\cdot ^{\\circ}C$)) на $20 ^{\\circ}C$?","o":["21000 Дж","2100 Дж","42000 Дж","84000 Дж"],"a":2},{"t":"Сила тока 5 А, сопротивление 5 Ом. Найдите напряжение.","o":["25 В","50 В","10 В","5 В"],"a":0},{"t":"Сила тока 3 А, сопротивление 2 Ом. Найдите напряжение.","o":["12 В","5 В","3 В","6 В"],"a":3},{"t":"Воду массой 1 кг нагрели от $30 ^{\\circ}C$ до $90 ^{\\circ}C (c = 4200)$. Сколько теплоты получено?","o":["252000 Дж","504000 Дж","4200 Дж","126000 Дж"],"a":0},{"t":"Два резистора 10 Ом и 4 Ом соединены последовательно. Общее сопротивление?","o":["14 Ом","28 Ом","40 Ом","6 Ом"],"a":0},{"t":"Напряжение 6 В, сопротивление 4 Ом. Найдите силу тока (закон Ома).","o":["6 А","1,5 А","4 А","24 А"],"a":1},{"t":"Сила тока 1 А, сопротивление 2 Ом. Найдите напряжение.","o":["4 В","3 В","2 В","1 В"],"a":2},{"t":"Сила тока 3 А, сопротивление 10 Ом. Найдите напряжение.","o":["60 В","3 В","30 В","13 В"],"a":2},{"t":"Напряжение 36 В, сила тока 2 А. Найдите сопротивление.","o":["2 Ом","72 Ом","36 Ом","18 Ом"],"a":3},{"t":"Напряжение 220 В, сила тока 1 А. Найдите мощность тока.","o":["221 Вт","1 Вт","220 Вт","440 Вт"],"a":2},{"t":"Через проводник идёт ток 10 А в течение 20 с. Найдите прошедший заряд.","o":["10 Кл","20 Кл","200 Кл","400 Кл"],"a":2},{"t":"Сколько теплоты выделит 1 кг спирта при полном сгорании ($q = 27000000$ Дж/кг)?","o":["81000000 Дж","27000000 Дж","54000000 Дж","13500000 Дж"],"a":1},{"t":"Воду массой 2 кг нагрели от $20 ^{\\circ}C$ до $80 ^{\\circ}C (c = 4200)$. Сколько теплоты получено?","o":["1008000 Дж","8400 Дж","252000 Дж","504000 Дж"],"a":3},{"t":"Ток 2 А идёт через резистор 10 Ом в течение 20 с. Теплота (закон Джоуля–Ленца)?","o":["1600 Дж","400 Дж","20 Дж","800 Дж"],"a":3},{"t":"Два резистора 3 Ом и 8 Ом соединены последовательно. Общее сопротивление?","o":["24 Ом","11 Ом","22 Ом","5 Ом"],"a":1},{"t":"Напряжение 6 В, сила тока 3 А. Найдите сопротивление.","o":["3 Ом","4 Ом","2 Ом","6 Ом"],"a":2},{"t":"Напряжение 36 В, сопротивление 2 Ом. Найдите силу тока (закон Ома).","o":["72 А","36 А","18 А","2 А"],"a":2},{"t":"Напряжение 12 В, сила тока 2 А. Найдите мощность тока.","o":["24 Вт","14 Вт","48 Вт","12 Вт"],"a":0},{"t":"Сколько теплоты выделит 2 кг спирта при полном сгорании ($q = 27000000$ Дж/кг)?","o":["54000000 Дж","27000000 Дж","162000000 Дж","108000000 Дж"],"a":0},{"t":"Напряжение 48 В, сопротивление 4 Ом. Найдите силу тока (закон Ома).","o":["192 А","48 А","4 А","12 А"],"a":3},{"t":"Два резистора 10 Ом и 6 Ом соединены последовательно. Общее сопротивление?","o":["32 Ом","16 Ом","4 Ом","60 Ом"],"a":1},{"t":"Сколько теплоты нужно для нагрева 2 кг алюминия ($c = 900$ Дж/(кг$\\cdot ^{\\circ}C$)) на $10 ^{\\circ}C$?","o":["18000 Дж","9000 Дж","1800 Дж","36000 Дж"],"a":0},{"t":"Сколько теплоты выделит 5 кг спирта при полном сгорании ($q = 27000000$ Дж/кг)?","o":["270000000 Дж","67500000 Дж","27000000 Дж","135000000 Дж"],"a":3},{"t":"Сколько теплоты выделит 3 кг бензина при полном сгорании ($q = 46000000$ Дж/кг)?","o":["46000000 Дж","69000000 Дж","276000000 Дж","138000000 Дж"],"a":3},{"t":"Сколько теплоты нужно для нагрева 0,5 кг меди ($c = 400$ Дж/(кг$\\cdot ^{\\circ}C$)) на $50 ^{\\circ}C$?","o":["200 Дж","5000 Дж","20000 Дж","10000 Дж"],"a":3},{"t":"Мощность прибора 60 Вт, время работы 60 с. Найдите работу тока.","o":["1800 Дж","60 Дж","7200 Дж","3600 Дж"],"a":3},{"t":"Мощность прибора 100 Вт, время работы 60 с. Найдите работу тока.","o":["6000 Дж","12000 Дж","60 Дж","100 Дж"],"a":0},{"t":"Напряжение 12 В, сила тока 2 А. Найдите сопротивление.","o":["6 Ом","24 Ом","12 Ом","2 Ом"],"a":0},{"t":"Напряжение 12 В, сила тока 1 А. Найдите сопротивление.","o":["24 Ом","36 Ом","12 Ом","1 Ом"],"a":2},{"t":"Сколько теплоты нужно для нагрева 2 кг меди ($c = 400$ Дж/(кг$\\cdot ^{\\circ}C$)) на $50 ^{\\circ}C$?","o":["40000 Дж","20000 Дж","80000 Дж","800 Дж"],"a":0},{"t":"Напряжение 36 В, сила тока 1 А. Найдите сопротивление.","o":["1 Ом","108 Ом","36 Ом","72 Ом"],"a":2},{"t":"Напряжение 48 В, сопротивление 3 Ом. Найдите силу тока (закон Ома).","o":["16 А","3 А","48 А","144 А"],"a":0},{"t":"Сколько теплоты нужно, чтобы расплавить 2 кг олова при температуре плавления ($\\lambda = 80000$ Дж/кг)?","o":["80000 Дж","160000 Дж","320000 Дж","480000 Дж"],"a":1},{"t":"Сколько теплоты нужно для нагрева 2 кг алюминия ($c = 900$ Дж/(кг$\\cdot ^{\\circ}C$)) на $50 ^{\\circ}C$?","o":["45000 Дж","180000 Дж","90000 Дж","1800 Дж"],"a":2},{"t":"Сколько теплоты нужно для нагрева 2 кг воды ($c = 4200$ Дж/(кг$\\cdot ^{\\circ}C$)) на $10 ^{\\circ}C$?","o":["84000 Дж","8400 Дж","42000 Дж","168000 Дж"],"a":0},{"t":"Два резистора 2 Ом и 6 Ом соединены последовательно. Общее сопротивление?","o":["16 Ом","8 Ом","4 Ом","12 Ом"],"a":1},{"t":"Сколько теплоты нужно для нагрева 0,5 кг меди ($c = 400$ Дж/(кг$\\cdot ^{\\circ}C$)) на $30 ^{\\circ}C$?","o":["3000 Дж","12000 Дж","6000 Дж","200 Дж"],"a":2},{"t":"Ток 2 А идёт через резистор 10 Ом в течение 10 с. Теплота (закон Джоуля–Ленца)?","o":["800 Дж","20 Дж","200 Дж","400 Дж"],"a":3},{"t":"Через проводник идёт ток 2 А в течение 5 с. Найдите прошедший заряд.","o":["2 Кл","5 Кл","10 Кл","20 Кл"],"a":2},{"t":"Напряжение 36 В, сила тока 2 А. Найдите мощность тока.","o":["38 Вт","144 Вт","36 Вт","72 Вт"],"a":3},{"t":"Ток 5 А идёт через резистор 5 Ом в течение 5 с. Теплота (закон Джоуля–Ленца)?","o":["25 Дж","625 Дж","125 Дж","1250 Дж"],"a":1},{"t":"Напряжение 36 В, сила тока 3 А. Найдите сопротивление.","o":["36 Ом","3 Ом","24 Ом","12 Ом"],"a":3},{"t":"Воду массой 2 кг нагрели от $30 ^{\\circ}C$ до $90 ^{\\circ}C (c = 4200)$. Сколько теплоты получено?","o":["252000 Дж","504000 Дж","8400 Дж","1008000 Дж"],"a":1},{"t":"Ток 2 А идёт через резистор 4 Ом в течение 20 с. Теплота (закон Джоуля–Ленца)?","o":["320 Дж","640 Дж","160 Дж","8 Дж"],"a":0},{"t":"Сколько теплоты нужно, чтобы расплавить 0,5 кг олова при температуре плавления ($\\lambda = 80000$ Дж/кг)?","o":["80000 Дж","120000 Дж","40000 Дж","20000 Дж"],"a":2},{"t":"Напряжение 24 В, сила тока 3 А. Найдите мощность тока.","o":["144 Вт","72 Вт","27 Вт","24 Вт"],"a":1},{"t":"Сколько теплоты нужно, чтобы расплавить 0,5 кг льда при температуре плавления ($\\lambda = 330000$ Дж/кг)?","o":["82500 Дж","165000 Дж","495000 Дж","330000 Дж"],"a":1},{"t":"Сила тока 5 А, сопротивление 10 Ом. Найдите напряжение.","o":["15 В","50 В","100 В","5 В"],"a":1},{"t":"Два резистора 5 Ом и 4 Ом соединены последовательно. Общее сопротивление?","o":["9 Ом","18 Ом","20 Ом","1 Ом"],"a":0},{"t":"Ток 5 А идёт через резистор 4 Ом в течение 20 с. Теплота (закон Джоуля–Ленца)?","o":["2000 Дж","400 Дж","4000 Дж","20 Дж"],"a":0},{"t":"Напряжение 6 В, сопротивление 6 Ом. Найдите силу тока (закон Ома).","o":["36 А","2 А","6 А","1 А"],"a":3},{"t":"Через проводник идёт ток 3 А в течение 10 с. Найдите прошедший заряд.","o":["30 Кл","3 Кл","60 Кл","10 Кл"],"a":0},{"t":"Напряжение 220 В, сила тока 5 А. Найдите мощность тока.","o":["1100 Вт","220 Вт","225 Вт","2200 Вт"],"a":0},{"t":"Сколько теплоты нужно для нагрева 1 кг меди ($c = 400$ Дж/(кг$\\cdot ^{\\circ}C$)) на $20 ^{\\circ}C$?","o":["400 Дж","16000 Дж","8000 Дж","4000 Дж"],"a":2},{"t":"Напряжение 36 В, сила тока 5 А. Найдите мощность тока.","o":["36 Вт","41 Вт","180 Вт","360 Вт"],"a":2},{"t":"Ток 1 А идёт через резистор 2 Ом в течение 5 с. Теплота (закон Джоуля–Ленца)?","o":["10 Дж","5 Дж","2 Дж","20 Дж"],"a":0},{"t":"Через проводник идёт ток 5 А в течение 10 с. Найдите прошедший заряд.","o":["10 Кл","5 Кл","100 Кл","50 Кл"],"a":3},{"t":"Сколько теплоты выделит 2 кг дров при полном сгорании ($q = 13000000$ Дж/кг)?","o":["26000000 Дж","78000000 Дж","52000000 Дж","13000000 Дж"],"a":0},{"t":"Мощность прибора 1000 Вт, время работы 100 с. Найдите работу тока.","o":["100 Дж","100000 Дж","1000 Дж","200000 Дж"],"a":1},{"t":"Два резистора 5 Ом и 12 Ом соединены последовательно. Общее сопротивление?","o":["17 Ом","34 Ом","60 Ом","7 Ом"],"a":0},{"t":"Ток 3 А идёт через резистор 5 Ом в течение 10 с. Теплота (закон Джоуля–Ленца)?","o":["450 Дж","150 Дж","15 Дж","900 Дж"],"a":0},{"t":"Через проводник идёт ток 10 А в течение 10 с. Найдите прошедший заряд.","o":["200 Кл","100 Кл","10 Кл","50 Кл"],"a":1},{"t":"Сколько теплоты нужно для нагрева 3 кг воды ($c = 4200$ Дж/(кг$\\cdot ^{\\circ}C$)) на $10 ^{\\circ}C$?","o":["252000 Дж","63000 Дж","126000 Дж","42000 Дж"],"a":2},{"t":"Ток 1 А идёт через резистор 4 Ом в течение 5 с. Теплота (закон Джоуля–Ленца)?","o":["4 Дж","10 Дж","40 Дж","20 Дж"],"a":3},{"t":"Воду массой 1 кг нагрели от $20 ^{\\circ}C$ до $60 ^{\\circ}C (c = 4200)$. Сколько теплоты получено?","o":["168000 Дж","84000 Дж","336000 Дж","4200 Дж"],"a":0},{"t":"Воду массой 1 кг нагрели от $20 ^{\\circ}C$ до $80 ^{\\circ}C (c = 4200)$. Сколько теплоты получено?","o":["252000 Дж","126000 Дж","4200 Дж","504000 Дж"],"a":0},{"t":"Мощность прибора 40 Вт, время работы 100 с. Найдите работу тока.","o":["40 Дж","4000 Дж","8000 Дж","100 Дж"],"a":1},{"t":"Напряжение 12 В, сила тока 5 А. Найдите мощность тока.","o":["12 Вт","120 Вт","60 Вт","17 Вт"],"a":2},{"t":"Напряжение 24 В, сила тока 4 А. Найдите сопротивление.","o":["4 Ом","24 Ом","6 Ом","12 Ом"],"a":2},{"t":"Сколько теплоты нужно для нагрева 0,5 кг стали ($c = 500$ Дж/(кг$\\cdot ^{\\circ}C$)) на $20 ^{\\circ}C$?","o":["2500 Дж","10000 Дж","5000 Дж","250 Дж"],"a":2},{"t":"Сила тока 4 А, сопротивление 10 Ом. Найдите напряжение.","o":["80 В","40 В","14 В","4 В"],"a":1},{"t":"Мощность прибора 2000 Вт, время работы 100 с. Найдите работу тока.","o":["2000 Дж","100 Дж","200000 Дж","400000 Дж"],"a":2},{"t":"Два резистора 5 Ом и 8 Ом соединены последовательно. Общее сопротивление?","o":["26 Ом","40 Ом","13 Ом","3 Ом"],"a":2},{"t":"Ток 2 А идёт через резистор 5 Ом в течение 5 с. Теплота (закон Джоуля–Ленца)?","o":["200 Дж","100 Дж","10 Дж","50 Дж"],"a":1},{"t":"Сколько теплоты нужно, чтобы расплавить 1 кг олова при температуре плавления ($\\lambda = 80000$ Дж/кг)?","o":["40000 Дж","240000 Дж","160000 Дж","80000 Дж"],"a":3},{"t":"Сколько теплоты нужно для нагрева 3 кг воды ($c = 4200$ Дж/(кг$\\cdot ^{\\circ}C$)) на $20 ^{\\circ}C$?","o":["84000 Дж","126000 Дж","504000 Дж","252000 Дж"],"a":3},{"t":"Два резистора 10 Ом и 8 Ом соединены последовательно. Общее сопротивление?","o":["2 Ом","18 Ом","80 Ом","36 Ом"],"a":1},{"t":"Напряжение 220 В, сопротивление 4 Ом. Найдите силу тока (закон Ома).","o":["220 А","4 А","55 А","880 А"],"a":2},{"t":"Напряжение 220 В, сопротивление 2 Ом. Найдите силу тока (закон Ома).","o":["110 А","440 А","2 А","220 А"],"a":0},{"t":"Через проводник идёт ток 3 А в течение 4 с. Найдите прошедший заряд.","o":["4 Кл","12 Кл","3 Кл","24 Кл"],"a":1},{"t":"Сколько теплоты нужно для нагрева 3 кг стали ($c = 500$ Дж/(кг$\\cdot ^{\\circ}C$)) на $30 ^{\\circ}C$?","o":["15000 Дж","90000 Дж","45000 Дж","22500 Дж"],"a":2},{"t":"Через проводник идёт ток 2 А в течение 4 с. Найдите прошедший заряд.","o":["4 Кл","16 Кл","8 Кл","2 Кл"],"a":2},{"t":"Сила тока 1 А, сопротивление 10 Ом. Найдите напряжение.","o":["10 В","1 В","20 В","11 В"],"a":0},{"t":"Мощность прибора 60 Вт, время работы 20 с. Найдите работу тока.","o":["2400 Дж","60 Дж","20 Дж","1200 Дж"],"a":3},{"t":"Сколько теплоты нужно для нагрева 1 кг алюминия ($c = 900$ Дж/(кг$\\cdot ^{\\circ}C$)) на $30 ^{\\circ}C$?","o":["900 Дж","27000 Дж","54000 Дж","13500 Дж"],"a":1},{"t":"Сколько теплоты выделит 1 кг бензина при полном сгорании ($q = 46000000$ Дж/кг)?","o":["23000000 Дж","92000000 Дж","138000000 Дж","46000000 Дж"],"a":3},{"t":"Воду массой 1 кг нагрели от $30 ^{\\circ}C$ до $80 ^{\\circ}C (c = 4200)$. Сколько теплоты получено?","o":["105000 Дж","420000 Дж","4200 Дж","210000 Дж"],"a":3},{"t":"Сколько теплоты нужно для нагрева 2 кг меди ($c = 400$ Дж/(кг$\\cdot ^{\\circ}C$)) на $20 ^{\\circ}C$?","o":["32000 Дж","8000 Дж","16000 Дж","800 Дж"],"a":2},{"t":"Сколько теплоты нужно, чтобы расплавить 1 кг льда при температуре плавления ($\\lambda = 330000$ Дж/кг)?","o":["330000 Дж","660000 Дж","990000 Дж","165000 Дж"],"a":0},{"t":"Напряжение 6 В, сопротивление 12 Ом. Найдите силу тока (закон Ома).","o":["12 А","6 А","0,5 А","72 А"],"a":2},{"t":"Напряжение 12 В, сила тока 3 А. Найдите мощность тока.","o":["15 Вт","72 Вт","36 Вт","12 Вт"],"a":2},{"t":"Ток 2 А идёт через резистор 2 Ом в течение 10 с. Теплота (закон Джоуля–Ленца)?","o":["160 Дж","80 Дж","40 Дж","4 Дж"],"a":1},{"t":"Ток 3 А идёт через резистор 10 Ом в течение 10 с. Теплота (закон Джоуля–Ленца)?","o":["900 Дж","30 Дж","1800 Дж","300 Дж"],"a":0},{"t":"Воду массой 2 кг нагрели от $20 ^{\\circ}C$ до $90 ^{\\circ}C (c = 4200)$. Сколько теплоты получено?","o":["8400 Дж","294000 Дж","1176000 Дж","588000 Дж"],"a":3},{"t":"Напряжение 36 В, сила тока 4 А. Найдите сопротивление.","o":["18 Ом","36 Ом","9 Ом","4 Ом"],"a":2},{"t":"Мощность прибора 60 Вт, время работы 100 с. Найдите работу тока.","o":["6000 Дж","60 Дж","12000 Дж","100 Дж"],"a":0},{"t":"Ток 1 А идёт через резистор 5 Ом в течение 10 с. Теплота (закон Джоуля–Ленца)?","o":["100 Дж","25 Дж","5 Дж","50 Дж"],"a":3},{"t":"Через проводник идёт ток 10 А в течение 4 с. Найдите прошедший заряд.","o":["4 Кл","80 Кл","10 Кл","40 Кл"],"a":3},{"t":"Напряжение 12 В, сила тока 1 А. Найдите мощность тока.","o":["12 Вт","24 Вт","13 Вт","1 Вт"],"a":0},{"t":"Сила тока 2 А, сопротивление 3 Ом. Найдите напряжение.","o":["12 В","2 В","5 В","6 В"],"a":3},{"t":"Ток 5 А идёт через резистор 10 Ом в течение 5 с. Теплота (закон Джоуля–Ленца)?","o":["2500 Дж","1250 Дж","50 Дж","250 Дж"],"a":1},{"t":"Сколько теплоты выделит 3 кг спирта при полном сгорании ($q = 27000000$ Дж/кг)?","o":["27000000 Дж","40500000 Дж","162000000 Дж","81000000 Дж"],"a":3},{"t":"Сколько теплоты нужно для нагрева 1 кг стали ($c = 500$ Дж/(кг$\\cdot ^{\\circ}C$)) на $10 ^{\\circ}C$?","o":["500 Дж","2500 Дж","5000 Дж","10000 Дж"],"a":2},{"t":"Сколько теплоты выделит 5 кг бензина при полном сгорании ($q = 46000000$ Дж/кг)?","o":["115000000 Дж","460000000 Дж","46000000 Дж","230000000 Дж"],"a":3},{"t":"Мощность прибора 40 Вт, время работы 60 с. Найдите работу тока.","o":["2400 Дж","60 Дж","40 Дж","4800 Дж"],"a":0},{"t":"Воду массой 2 кг нагрели от $30 ^{\\circ}C$ до $60 ^{\\circ}C (c = 4200)$. Сколько теплоты получено?","o":["8400 Дж","252000 Дж","504000 Дж","126000 Дж"],"a":1},{"t":"Мощность прибора 60 Вт, время работы 10 с. Найдите работу тока.","o":["600 Дж","10 Дж","60 Дж","1200 Дж"],"a":0},{"t":"Напряжение 6 В, сопротивление 3 Ом. Найдите силу тока (закон Ома).","o":["18 А","2 А","3 А","6 А"],"a":1},{"t":"Сколько теплоты нужно для нагрева 3 кг воды ($c = 4200$ Дж/(кг$\\cdot ^{\\circ}C$)) на $50 ^{\\circ}C$?","o":["1260000 Дж","630000 Дж","315000 Дж","210000 Дж"],"a":1},{"t":"Ток 1 А идёт через резистор 2 Ом в течение 20 с. Теплота (закон Джоуля–Ленца)?","o":["2 Дж","20 Дж","80 Дж","40 Дж"],"a":3},{"t":"Мощность прибора 40 Вт, время работы 20 с. Найдите работу тока.","o":["800 Дж","40 Дж","20 Дж","1600 Дж"],"a":0},{"t":"Напряжение 24 В, сила тока 5 А. Найдите мощность тока.","o":["24 Вт","29 Вт","120 Вт","240 Вт"],"a":2},{"t":"Напряжение 6 В, сопротивление 2 Ом. Найдите силу тока (закон Ома).","o":["12 А","2 А","6 А","3 А"],"a":3},{"t":"Напряжение 12 В, сопротивление 12 Ом. Найдите силу тока (закон Ома).","o":["2 А","1 А","144 А","12 А"],"a":1},{"t":"Мощность прибора 100 Вт, время работы 20 с. Найдите работу тока.","o":["20 Дж","4000 Дж","100 Дж","2000 Дж"],"a":3},{"t":"Напряжение 12 В, сопротивление 2 Ом. Найдите силу тока (закон Ома).","o":["2 А","6 А","24 А","12 А"],"a":1},{"t":"Сколько теплоты выделит 5 кг дров при полном сгорании ($q = 13000000$ Дж/кг)?","o":["13000000 Дж","65000000 Дж","32500000 Дж","130000000 Дж"],"a":1},{"t":"Напряжение 220 В, сопротивление 3 Ом. Найдите силу тока (закон Ома).","o":["220 А","3 А","660 А","73,3333 А"],"a":3},{"t":"Мощность прибора 2000 Вт, время работы 10 с. Найдите работу тока.","o":["40000 Дж","20000 Дж","2000 Дж","10 Дж"],"a":1},{"t":"Два резистора 2 Ом и 12 Ом соединены последовательно. Общее сопротивление?","o":["10 Ом","28 Ом","24 Ом","14 Ом"],"a":3},{"t":"Через проводник идёт ток 3 А в течение 20 с. Найдите прошедший заряд.","o":["60 Кл","20 Кл","120 Кл","3 Кл"],"a":0},{"t":"Сила тока 5 А, сопротивление 2 Ом. Найдите напряжение.","o":["7 В","10 В","5 В","20 В"],"a":1},{"t":"Воду массой 2 кг нагрели от $20 ^{\\circ}C$ до $60 ^{\\circ}C (c = 4200)$. Сколько теплоты получено?","o":["336000 Дж","672000 Дж","8400 Дж","168000 Дж"],"a":0},{"t":"Ток 3 А идёт через резистор 4 Ом в течение 5 с. Теплота (закон Джоуля–Ленца)?","o":["12 Дж","60 Дж","180 Дж","360 Дж"],"a":2},{"t":"Ток 3 А идёт через резистор 2 Ом в течение 10 с. Теплота (закон Джоуля–Ленца)?","o":["180 Дж","60 Дж","6 Дж","360 Дж"],"a":0},{"t":"Напряжение 48 В, сопротивление 2 Ом. Найдите силу тока (закон Ома).","o":["48 А","96 А","2 А","24 А"],"a":3},{"t":"Напряжение 36 В, сила тока 1 А. Найдите мощность тока.","o":["37 Вт","1 Вт","72 Вт","36 Вт"],"a":3},{"t":"Мощность прибора 1000 Вт, время работы 10 с. Найдите работу тока.","o":["1000 Дж","10 Дж","20000 Дж","10000 Дж"],"a":3},{"t":"Напряжение 24 В, сила тока 2 А. Найдите мощность тока.","o":["24 Вт","96 Вт","48 Вт","26 Вт"],"a":2},{"t":"Напряжение 12 В, сопротивление 3 Ом. Найдите силу тока (закон Ома).","o":["4 А","12 А","3 А","36 А"],"a":0},{"t":"Напряжение 220 В, сопротивление 6 Ом. Найдите силу тока (закон Ома).","o":["220 А","1320 А","6 А","36,6667 А"],"a":3},{"t":"Сколько теплоты нужно для нагрева 2 кг стали ($c = 500$ Дж/(кг$\\cdot ^{\\circ}C$)) на $20 ^{\\circ}C$?","o":["20000 Дж","40000 Дж","1000 Дж","10000 Дж"],"a":0},{"t":"Напряжение 220 В, сила тока 3 А. Найдите мощность тока.","o":["660 Вт","220 Вт","1320 Вт","223 Вт"],"a":0},{"t":"Ток 3 А идёт через резистор 10 Ом в течение 20 с. Теплота (закон Джоуля–Ленца)?","o":["3600 Дж","600 Дж","30 Дж","1800 Дж"],"a":3},{"t":"Напряжение 36 В, сопротивление 3 Ом. Найдите силу тока (закон Ома).","o":["108 А","12 А","36 А","3 А"],"a":1},{"t":"Сколько теплоты нужно для нагрева 1 кг алюминия ($c = 900$ Дж/(кг$\\cdot ^{\\circ}C$)) на $10 ^{\\circ}C$?","o":["900 Дж","18000 Дж","4500 Дж","9000 Дж"],"a":3},{"t":"Напряжение 24 В, сопротивление 6 Ом. Найдите силу тока (закон Ома).","o":["6 А","4 А","144 А","24 А"],"a":1},{"t":"Два резистора 3 Ом и 6 Ом соединены последовательно. Общее сопротивление?","o":["18 Ом","9 Ом","6 Ом","3 Ом"],"a":1},{"t":"Сколько теплоты нужно для нагрева 1 кг стали ($c = 500$ Дж/(кг$\\cdot ^{\\circ}C$)) на $50 ^{\\circ}C$?","o":["500 Дж","50000 Дж","25000 Дж","12500 Дж"],"a":2},{"t":"Сколько теплоты нужно для нагрева 2 кг меди ($c = 400$ Дж/(кг$\\cdot ^{\\circ}C$)) на $30 ^{\\circ}C$?","o":["12000 Дж","48000 Дж","800 Дж","24000 Дж"],"a":3},{"t":"Сила тока 3 А, сопротивление 3 Ом. Найдите напряжение.","o":["3 В","6 В","18 В","9 В"],"a":3},{"t":"Сила тока 2 А, сопротивление 20 Ом. Найдите напряжение.","o":["22 В","80 В","2 В","40 В"],"a":3},{"t":"Через проводник идёт ток 5 А в течение 5 с. Найдите прошедший заряд.","o":["12 Кл","50 Кл","5 Кл","25 Кл"],"a":3},{"t":"Через проводник идёт ток 3 А в течение 5 с. Найдите прошедший заряд.","o":["5 Кл","30 Кл","15 Кл","3 Кл"],"a":2},{"t":"Сколько теплоты нужно для нагрева 2 кг алюминия ($c = 900$ Дж/(кг$\\cdot ^{\\circ}C$)) на $20 ^{\\circ}C$?","o":["18000 Дж","1800 Дж","72000 Дж","36000 Дж"],"a":3},{"t":"Напряжение 48 В, сопротивление 6 Ом. Найдите силу тока (закон Ома).","o":["48 А","8 А","288 А","6 А"],"a":1},{"t":"Ток 5 А идёт через резистор 4 Ом в течение 5 с. Теплота (закон Джоуля–Ленца)?","o":["500 Дж","1000 Дж","20 Дж","100 Дж"],"a":0}],"short":[{"t":"Как называется прибор для измерения силы тока?","a":["амперметр"],"h":"Краткий ответ"},{"t":"Как называется прибор для измерения напряжения?","a":["вольтметр"],"h":"Краткий ответ"},{"t":"Как называется прибор для измерения относительной влажности?","a":["гигрометр","психрометр"],"h":"Краткий ответ"},{"t":"Как называется единица силы тока (название)?","a":["ампер"],"h":"Краткий ответ"},{"t":"Как называется единица напряжения (название)?","a":["вольт"],"h":"Краткий ответ"},{"t":"Как называется единица сопротивления (название)?","a":["ом"],"h":"Краткий ответ"},{"t":"Назовите три вида теплопередачи (через запятую).","a":["теплопроводность конвекция излучение","теплопроводность, конвекция, излучение"],"h":"Краткий ответ"},{"t":"Как называется явление возникновения тока при изменении магнитного поля?","a":["электромагнитная индукция","индукция"],"h":"Краткий ответ"},{"t":"Как называется опыт, показавший связь тока и магнитного поля (по фамилии)?","a":["опыт эрстеда","эрстеда","эрстед"],"h":"Краткий ответ"},{"t":"Как называется устройство — катушка с током и железным сердечником?","a":["электромагнит"],"h":"Краткий ответ"},{"t":"Назовите учёных, по чьим фамилиям назван закон о теплоте тока.","a":["джоуля ленца","джоуль ленц","джоуля-ленца","джоуль-ленц"],"h":"Краткий ответ"},{"t":"Что преобразует электрический ток в механическое движение?","a":["электродвигатель","двигатель"],"h":"Краткий ответ"},{"t":"$I = 3$ А, $R = 5$ Ом, $t = 10$ с. Теплота (Дж)?","a":["450"],"h":"Ответ в Дж"},{"t":"$I = 2$ А, $R = 10$ Ом. Напряжение (В)?","a":["20"],"h":"Ответ в В"},{"t":"$U = 36$ В, $R = 12$ Ом. Сила тока (А)?","a":["3"],"h":"Ответ в А"},{"t":"$U = 6$ В, $R = 2$ Ом. Сила тока (А)?","a":["3"],"h":"Ответ в А"},{"t":"$I = 3$ А, $R = 4$ Ом, $t = 5$ с. Теплота (Дж)?","a":["180"],"h":"Ответ в Дж"},{"t":"$c = 900$ Дж/(кг$\\cdot ^{\\circ}C), m = 1$ кг, $\\Delta t = 30 ^{\\circ}C$. Теплота нагрева (Дж)?","a":["27000"],"h":"Ответ в Дж"},{"t":"$U = 6$ В, $R = 12$ Ом. Сила тока (А)?","a":["0,5","0.5"],"h":"Ответ в А"},{"t":"$c = 4200$ Дж/(кг$\\cdot ^{\\circ}C), m = 2$ кг, $\\Delta t = 30 ^{\\circ}C$. Теплота нагрева (Дж)?","a":["252000"],"h":"Ответ в Дж"},{"t":"Последовательно: 3 Ом и 6 Ом. Общее сопротивление (Ом)?","a":["9"],"h":"Ответ в Ом"},{"t":"$I = 3$ А, $R = 5$ Ом, $t = 5$ с. Теплота (Дж)?","a":["225"],"h":"Ответ в Дж"},{"t":"Последовательно: 5 Ом и 8 Ом. Общее сопротивление (Ом)?","a":["13"],"h":"Ответ в Ом"},{"t":"Последовательно: 2 Ом и 6 Ом. Общее сопротивление (Ом)?","a":["8"],"h":"Ответ в Ом"},{"t":"$U = 12$ В, $I = 3$ А. Мощность тока (Вт)?","a":["36"],"h":"Ответ в Вт"},{"t":"$P = 100$ Вт, $t = 20$ с. Работа тока (Дж)?","a":["2000"],"h":"Ответ в Дж"},{"t":"$I = 3$ А, $R = 4$ Ом, $t = 10$ с. Теплота (Дж)?","a":["360"],"h":"Ответ в Дж"},{"t":"$I = 1$ А, $R = 3$ Ом. Напряжение (В)?","a":["3"],"h":"Ответ в В"},{"t":"$I = 4$ А, $R = 10$ Ом. Напряжение (В)?","a":["40"],"h":"Ответ в В"},{"t":"$I = 10$ А, $t = 20$ с. Заряд (Кл)?","a":["200"],"h":"Ответ в Кл"},{"t":"$q = 46000000$ Дж/кг, $m = 2$ кг. Теплота сгорания (Дж)?","a":["92000000"],"h":"Ответ в Дж"},{"t":"Последовательно: 10 Ом и 8 Ом. Общее сопротивление (Ом)?","a":["18"],"h":"Ответ в Ом"},{"t":"$U = 12$ В, $I = 5$ А. Мощность тока (Вт)?","a":["60"],"h":"Ответ в Вт"},{"t":"$U = 24$ В, $I = 2$ А. Мощность тока (Вт)?","a":["48"],"h":"Ответ в Вт"},{"t":"$I = 5$ А, $t = 4$ с. Заряд (Кл)?","a":["20"],"h":"Ответ в Кл"},{"t":"$U = 6$ В, $R = 6$ Ом. Сила тока (А)?","a":["1"],"h":"Ответ в А"},{"t":"$U = 48$ В, $R = 2$ Ом. Сила тока (А)?","a":["24"],"h":"Ответ в А"},{"t":"$I = 2$ А, $t = 20$ с. Заряд (Кл)?","a":["40"],"h":"Ответ в Кл"},{"t":"Последовательно: 3 Ом и 12 Ом. Общее сопротивление (Ом)?","a":["15"],"h":"Ответ в Ом"},{"t":"$U = 220$ В, $I = 5$ А. Мощность тока (Вт)?","a":["1100"],"h":"Ответ в Вт"},{"t":"$U = 36$ В, $R = 6$ Ом. Сила тока (А)?","a":["6"],"h":"Ответ в А"},{"t":"$I = 1$ А, $R = 4$ Ом, $t = 5$ с. Теплота (Дж)?","a":["20"],"h":"Ответ в Дж"},{"t":"$c = 900$ Дж/(кг$\\cdot ^{\\circ}C), m = 2$ кг, $\\Delta t = 20 ^{\\circ}C$. Теплота нагрева (Дж)?","a":["36000"],"h":"Ответ в Дж"},{"t":"$c = 4200$ Дж/(кг$\\cdot ^{\\circ}C), m = 2$ кг, $\\Delta t = 10 ^{\\circ}C$. Теплота нагрева (Дж)?","a":["84000"],"h":"Ответ в Дж"},{"t":"$I = 3$ А, $R = 3$ Ом. Напряжение (В)?","a":["9"],"h":"Ответ в В"},{"t":"$I = 10$ А, $t = 10$ с. Заряд (Кл)?","a":["100"],"h":"Ответ в Кл"},{"t":"$q = 13000000$ Дж/кг, $m = 3$ кг. Теплота сгорания (Дж)?","a":["39000000"],"h":"Ответ в Дж"},{"t":"$c = 400$ Дж/(кг$\\cdot ^{\\circ}C), m = 2$ кг, $\\Delta t = 10 ^{\\circ}C$. Теплота нагрева (Дж)?","a":["8000"],"h":"Ответ в Дж"},{"t":"$c = 400$ Дж/(кг$\\cdot ^{\\circ}C), m = 2$ кг, $\\Delta t = 20 ^{\\circ}C$. Теплота нагрева (Дж)?","a":["16000"],"h":"Ответ в Дж"},{"t":"$I = 4$ А, $R = 3$ Ом. Напряжение (В)?","a":["12"],"h":"Ответ в В"},{"t":"$I = 2$ А, $R = 10$ Ом, $t = 10$ с. Теплота (Дж)?","a":["400"],"h":"Ответ в Дж"},{"t":"$I = 1$ А, $R = 5$ Ом, $t = 10$ с. Теплота (Дж)?","a":["50"],"h":"Ответ в Дж"},{"t":"$I = 3$ А, $t = 10$ с. Заряд (Кл)?","a":["30"],"h":"Ответ в Кл"},{"t":"$c = 400$ Дж/(кг$\\cdot ^{\\circ}C), m = 1$ кг, $\\Delta t = 10 ^{\\circ}C$. Теплота нагрева (Дж)?","a":["4000"],"h":"Ответ в Дж"},{"t":"$P = 40$ Вт, $t = 60$ с. Работа тока (Дж)?","a":["2400"],"h":"Ответ в Дж"},{"t":"$I = 4$ А, $R = 5$ Ом. Напряжение (В)?","a":["20"],"h":"Ответ в В"},{"t":"$q = 27000000$ Дж/кг, $m = 3$ кг. Теплота сгорания (Дж)?","a":["81000000"],"h":"Ответ в Дж"},{"t":"$c = 900$ Дж/(кг$\\cdot ^{\\circ}C), m = 2$ кг, $\\Delta t = 10 ^{\\circ}C$. Теплота нагрева (Дж)?","a":["18000"],"h":"Ответ в Дж"},{"t":"$I = 3$ А, $R = 10$ Ом. Напряжение (В)?","a":["30"],"h":"Ответ в В"},{"t":"$U = 6$ В, $R = 4$ Ом. Сила тока (А)?","a":["1,5","1.5"],"h":"Ответ в А"},{"t":"$U = 24$ В, $R = 6$ Ом. Сила тока (А)?","a":["4"],"h":"Ответ в А"},{"t":"$P = 60$ Вт, $t = 10$ с. Работа тока (Дж)?","a":["600"],"h":"Ответ в Дж"},{"t":"$P = 40$ Вт, $t = 10$ с. Работа тока (Дж)?","a":["400"],"h":"Ответ в Дж"},{"t":"$I = 2$ А, $R = 4$ Ом, $t = 10$ с. Теплота (Дж)?","a":["160"],"h":"Ответ в Дж"},{"t":"Последовательно: 5 Ом и 6 Ом. Общее сопротивление (Ом)?","a":["11"],"h":"Ответ в Ом"},{"t":"$I = 2$ А, $t = 5$ с. Заряд (Кл)?","a":["10"],"h":"Ответ в Кл"},{"t":"$I = 3$ А, $t = 4$ с. Заряд (Кл)?","a":["12"],"h":"Ответ в Кл"},{"t":"$U = 220$ В, $I = 1$ А. Мощность тока (Вт)?","a":["220"],"h":"Ответ в Вт"},{"t":"$q = 27000000$ Дж/кг, $m = 2$ кг. Теплота сгорания (Дж)?","a":["54000000"],"h":"Ответ в Дж"},{"t":"Последовательно: 2 Ом и 8 Ом. Общее сопротивление (Ом)?","a":["10"],"h":"Ответ в Ом"},{"t":"$I = 10$ А, $t = 4$ с. Заряд (Кл)?","a":["40"],"h":"Ответ в Кл"},{"t":"$I = 2$ А, $t = 10$ с. Заряд (Кл)?","a":["20"],"h":"Ответ в Кл"},{"t":"$I = 2$ А, $R = 10$ Ом, $t = 5$ с. Теплота (Дж)?","a":["200"],"h":"Ответ в Дж"},{"t":"$I = 1$ А, $R = 4$ Ом, $t = 10$ с. Теплота (Дж)?","a":["40"],"h":"Ответ в Дж"},{"t":"$U = 48$ В, $R = 12$ Ом. Сила тока (А)?","a":["4"],"h":"Ответ в А"},{"t":"Последовательно: 10 Ом и 12 Ом. Общее сопротивление (Ом)?","a":["22"],"h":"Ответ в Ом"},{"t":"$P = 100$ Вт, $t = 60$ с. Работа тока (Дж)?","a":["6000"],"h":"Ответ в Дж"},{"t":"$q = 27000000$ Дж/кг, $m = 1$ кг. Теплота сгорания (Дж)?","a":["27000000"],"h":"Ответ в Дж"},{"t":"$U = 48$ В, $R = 3$ Ом. Сила тока (А)?","a":["16"],"h":"Ответ в А"},{"t":"$q = 46000000$ Дж/кг, $m = 1$ кг. Теплота сгорания (Дж)?","a":["46000000"],"h":"Ответ в Дж"}],"match":[{"t":"Соотнесите величину и единицу измерения","L":["Сила тока","Напряжение","Сопротивление","Количество теплоты"],"R":["Ампер (А)","Вольт (В)","Ом","Джоуль (Дж)"],"p":[0,1,2,3]},{"t":"Соотнесите прибор и измеряемую величину","L":["Амперметр","Вольтметр","Гигрометр","Термометр"],"R":["Силу тока","Напряжение","Влажность","Температуру"],"p":[0,1,2,3]},{"t":"Соотнесите вид теплопередачи и пример","L":["Теплопроводность","Конвекция","Излучение"],"R":["Нагрев ложки в чае","Прогрев комнаты батареей","Тепло от Солнца"],"p":[0,1,2]},{"t":"Соотнесите формулу и величину","L":["$Q = c \\cdot m \\cdot \\Delta t$","$I = \\frac{U}{R}$","$P = U \\cdot I$","$R = \\rho \\cdot \\frac{l}{S}$"],"R":["Теплота нагревания","Сила тока (закон Ома)","Мощность тока","Сопротивление проводника"],"p":[0,1,2,3]},{"t":"Соотнесите процесс и его суть","L":["Плавление","Кристаллизация","Испарение","Конденсация"],"R":["Твёрдое → жидкое","Жидкое → твёрдое","Жидкое → пар","Пар → жидкое"],"p":[0,1,2,3]},{"t":"Соотнесите учёного и закон/открытие","L":["Ом","Джоуль и Ленц","Кулон","Эрстед"],"R":["Закон для участка цепи","Теплота при токе","Взаимодействие зарядов","Магнитное действие тока"],"p":[0,1,2,3]},{"t":"Соотнесите удельную величину и её смысл","L":["Удельная теплоёмкость","Удельная теплота плавления","Удельная теплота парообразования","Удельная теплота сгорания"],"R":["Нагрев 1 кг на $1 ^{\\circ}C$","Плавление 1 кг","Испарение 1 кг","Сгорание 1 кг топлива"],"p":[0,1,2,3]},{"t":"Соотнесите соединение и правило","L":["Последовательное","Параллельное"],"R":["Сила тока одинакова, R складываются","Напряжение одинаково, токи складываются"],"p":[0,1]},{"t":"Соотнесите электрический прибор и его назначение","L":["Реостат","Лампа накаливания","Электрический звонок","Плавкий предохранитель"],"R":["Регулирует силу тока","Преобразует ток в свет","Преобразует ток в звук","Размыкает цепь при перегрузке"],"p":[0,1,2,3]},{"t":"Соотнесите формулу и величину","L":["$I = \\frac{q}{t}$","$U = \\frac{A}{q}$","$Q = I^{2} \\cdot R \\cdot t$"],"R":["Сила тока","Напряжение","Теплота (Джоуля–Ленца)"],"p":[0,1,2]},{"t":"Соотнесите магнитное понятие и факт","L":["Полюсы магнита","Одноимённые полюсы","Разноимённые полюсы","Магнитное поле Земли"],"R":["Северный и южный","Отталкиваются","Притягиваются","Защищает от космических частиц"],"p":[0,1,2,3]},{"t":"Соотнесите устройство и назначение","L":["Электродвигатель","Электрогенератор","Электромагнит","Предохранитель"],"R":["Ток → движение","Движение → ток","Создаёт магнитное поле","Защита от перегрузки"],"p":[0,1,2,3]},{"t":"Соотнесите единицу и величину","L":["Дж/(кг$\\cdot ^{\\circ}C$)","Дж/кг","Вт","Кл"],"R":["Удельная теплоёмкость","Удельная теплота","Мощность","Электрический заряд"],"p":[0,1,2,3]},{"t":"Соотнесите состояние и модель строения","L":["Газ","Жидкость","Кристалл"],"R":["Частицы далеко, движутся свободно","Частицы близко, но подвижны","Частицы в строгом порядке"],"p":[0,1,2]},{"t":"Соотнесите термин и определение","L":["Внутренняя энергия","Количество теплоты","Тепловое равновесие"],"R":["Энергия частиц тела","Энергия, переданная при теплообмене","Равенство температур тел"],"p":[0,1,2]},{"t":"Соотнесите символ и величину","L":["I","U","R","Q"],"R":["Сила тока","Напряжение","Сопротивление","Теплота"],"p":[0,1,2,3]}]}