{"choice":[{"t":"Какое понятие соответствует определению: «последовательность стадий: замысел, реализация, защита»?","o":["этапы проекта","исследовательский проект","проект","гипотеза"],"a":0},{"t":"Какое понятие соответствует определению: «средства, необходимые для выполнения (время, деньги, люди)»?","o":["ресурсы проекта","источник информации","предмет исследования","введение"],"a":0},{"t":"Что такое «предмет исследования»?","o":["определение действий, сроков и ресурсов проекта","процесс или явление, которое изучается","возможные события, мешающие достижению цели","конкретная сторона объекта, изучаемая в работе"],"a":3},{"t":"Какое понятие соответствует определению: «проект, направленный на получение новых знаний»?","o":["исследовательский проект","список литературы","методы исследования","защита проекта"],"a":0},{"t":"Какое понятие соответствует определению: «метод проверки гипотезы в управляемых условиях»?","o":["синтез","эксперимент","исследовательский проект","цель проекта"],"a":1},{"t":"Что такое «этапы проекта»?","o":["возможные события, мешающие достижению цели","последовательность стадий: замысел, реализация, защита","метод соединения частей в единое целое","средства, необходимые для выполнения (время, деньги, люди)"],"a":1},{"t":"Что такое «исследовательский проект»?","o":["проект, направленный на получение новых знаний","значимость и востребованность темы проекта","метод проверки гипотезы в управляемых условиях","ограниченная во времени деятельность для создания уникального результата"],"a":0},{"t":"Что такое «введение»?","o":["часть работы с целью, задачами и актуальностью","проект, направленный на получение новых знаний","процесс или явление, которое изучается","метод изучения путём разбиения целого на части"],"a":0},{"t":"Чем завершается работа над проектом?","o":["постановкой гипотезы","выбором темы","сбором литературы","защитой и выводами"],"a":3},{"t":"Что такое «продукт проекта»?","o":["материальный или информационный результат работы","определение действий, сроков и ресурсов проекта","проект с конкретным прикладным продуктом","ограниченная во времени деятельность для создания уникального результата"],"a":0},{"t":"Что такое «гипотеза»?","o":["выдача чужого труда за собственный","процесс или явление, которое изучается","научное предположение, требующее проверки","средства, необходимые для выполнения (время, деньги, люди)"],"a":2},{"t":"Что такое «рецензия»?","o":["определение действий, сроков и ресурсов проекта","отзыв с оценкой проектной работы","метод изучения путём разбиения целого на части","процесс или явление, которое изучается"],"a":1},{"t":"Что такое «проект»?","o":["научное предположение, требующее проверки","ограниченная во времени деятельность для создания уникального результата","материальный или информационный результат работы","метод сбора данных без вмешательства в процесс"],"a":1},{"t":"Какое понятие соответствует определению: «конкретная сторона объекта, изучаемая в работе»?","o":["предмет исследования","исследовательский проект","ресурсы проекта","анкетирование"],"a":0},{"t":"Что такое «актуальность»?","o":["конкретный шаг для достижения цели","способы получения и обработки информации","значимость и востребованность темы проекта","краткое обобщение результатов исследования"],"a":2},{"t":"Что такое «синтез»?","o":["метод соединения частей в единое целое","отзыв с оценкой проектной работы","метод изучения путём разбиения целого на части","конечный результат, ради которого выполняется проект"],"a":0},{"t":"Какое понятие соответствует определению: «конечный результат, ради которого выполняется проект»?","o":["синтез","методы исследования","цель проекта","вывод"],"a":2},{"t":"Какое понятие соответствует определению: «краткое обобщение результатов исследования»?","o":["вывод","эксперимент","цель проекта","планирование"],"a":0},{"t":"Какое понятие соответствует определению: «материальный или информационный результат работы»?","o":["гипотеза","заключение","продукт проекта","список литературы"],"a":2},{"t":"Какое понятие соответствует определению: «процесс или явление, которое изучается»?","o":["объект исследования","введение","практико-ориентированный проект","задача проекта"],"a":0},{"t":"Что такое «планирование»?","o":["часть работы с выводами по результатам","определение действий, сроков и ресурсов проекта","средства, необходимые для выполнения (время, деньги, люди)","метод сбора данных без вмешательства в процесс"],"a":1},{"t":"Что такое «вывод»?","o":["краткое обобщение результатов исследования","метод сбора данных с помощью опроса","возможные события, мешающие достижению цели","процесс или явление, которое изучается"],"a":0},{"t":"Какое понятие соответствует определению: «метод сбора данных без вмешательства в процесс»?","o":["наблюдение","задача проекта","рецензия","введение"],"a":0},{"t":"Что такое «практико-ориентированный проект»?","o":["публичное представление и обоснование результатов","ограниченная во времени деятельность для создания уникального результата","часть работы с выводами по результатам","проект с конкретным прикладным продуктом"],"a":3},{"t":"Что такое «список литературы»?","o":["книга, сайт, человек, дающие сведения по теме","перечень использованных источников","метод соединения частей в единое целое","определение действий, сроков и ресурсов проекта"],"a":1},{"t":"Какое понятие соответствует определению: «перечень использованных источников»?","o":["заключение","список литературы","вывод","предмет исследования"],"a":1},{"t":"Какое понятие соответствует определению: «часть работы с выводами по результатам»?","o":["задача проекта","рецензия","продукт проекта","заключение"],"a":3},{"t":"Какое понятие соответствует определению: «способы получения и обработки информации»?","o":["ресурсы проекта","методы исследования","задача проекта","практико-ориентированный проект"],"a":1},{"t":"Какое понятие соответствует определению: «метод сбора данных с помощью опроса»?","o":["ресурсы проекта","вывод","источник информации","анкетирование"],"a":3},{"t":"Какое понятие соответствует определению: «определение действий, сроков и ресурсов проекта»?","o":["наблюдение","этапы проекта","продукт проекта","планирование"],"a":3},{"t":"Какое понятие соответствует определению: «возможные события, мешающие достижению цели»?","o":["риски проекта","наблюдение","защита проекта","планирование"],"a":0},{"t":"Что такое «наблюдение»?","o":["метод соединения частей в единое целое","конкретный шаг для достижения цели","метод сбора данных без вмешательства в процесс","определение действий, сроков и ресурсов проекта"],"a":2},{"t":"Какое понятие соответствует определению: «метод соединения частей в единое целое»?","o":["рецензия","синтез","эксперимент","объект исследования"],"a":1},{"t":"Что такое «источник информации»?","o":["материальный или информационный результат работы","книга, сайт, человек, дающие сведения по теме","перечень использованных источников","краткое обобщение результатов исследования"],"a":1},{"t":"Какое понятие соответствует определению: «проект с конкретным прикладным продуктом»?","o":["исследовательский проект","рецензия","презентация","практико-ориентированный проект"],"a":3},{"t":"Что из перечисленного — метод исследования?","o":["заключение","введение","эксперимент","титул"],"a":2},{"t":"Какое понятие соответствует определению: «научное предположение, требующее проверки»?","o":["практико-ориентированный проект","предмет исследования","гипотеза","риски проекта"],"a":2},{"t":"Что такое «риски проекта»?","o":["часть работы с выводами по результатам","возможные события, мешающие достижению цели","научное предположение, требующее проверки","метод сбора данных с помощью опроса"],"a":1},{"t":"Что такое «аннотация»?","o":["материальный или информационный результат работы","конечный результат, ради которого выполняется проект","краткое изложение содержания работы","способы получения и обработки информации"],"a":2},{"t":"Что такое «презентация»?","o":["отзыв с оценкой проектной работы","метод сбора данных без вмешательства в процесс","ограниченная во времени деятельность для создания уникального результата","наглядное представление результатов проекта"],"a":3},{"t":"Что такое «заключение»?","o":["метод изучения путём разбиения целого на части","возможные события, мешающие достижению цели","конкретный шаг для достижения цели","часть работы с выводами по результатам"],"a":3},{"t":"Что такое «цель проекта»?","o":["метод изучения путём разбиения целого на части","метод сбора данных без вмешательства в процесс","конечный результат, ради которого выполняется проект","метод сбора данных с помощью опроса"],"a":2},{"t":"Что такое «объект исследования»?","o":["краткое изложение содержания работы","перечень использованных источников","процесс или явление, которое изучается","отзыв с оценкой проектной работы"],"a":2},{"t":"Какое понятие соответствует определению: «публичное представление и обоснование результатов»?","o":["рецензия","анкетирование","защита проекта","предмет исследования"],"a":2},{"t":"Где формулируются цель и задачи проекта?","o":["в приложении","в заключении","во введении","в списке литературы"],"a":2},{"t":"Какое понятие соответствует определению: «выдача чужого труда за собственный»?","o":["плагиат","планирование","список литературы","синтез"],"a":0},{"t":"Какое понятие соответствует определению: «метод изучения путём разбиения целого на части»?","o":["цель проекта","методы исследования","анкетирование","анализ"],"a":3},{"t":"Что такое «защита проекта»?","o":["публичное представление и обоснование результатов","выдача чужого труда за собственный","часть работы с целью, задачами и актуальностью","метод сбора данных без вмешательства в процесс"],"a":0},{"t":"Какое понятие соответствует определению: «ограниченная во времени деятельность для создания уникального результата»?","o":["защита проекта","продукт проекта","проект","синтез"],"a":2},{"t":"Что такое «задача проекта»?","o":["проект с конкретным прикладным продуктом","материальный или информационный результат работы","конкретный шаг для достижения цели","конечный результат, ради которого выполняется проект"],"a":2},{"t":"Как называется недопустимое копирование чужого текста?","o":["рецензия","плагиат","цитирование","аннотация"],"a":1},{"t":"Что такое гипотеза?","o":["название проекта","научное предположение, требующее проверки","список литературы","готовый вывод"],"a":1},{"t":"С чего начинается работа над проектом?","o":["с оформления списка литературы","с выбора темы и постановки цели","с защиты","с написания заключения"],"a":1},{"t":"Какое понятие соответствует определению: «часть работы с целью, задачами и актуальностью»?","o":["плагиат","цель проекта","синтез","введение"],"a":3},{"t":"Какое понятие соответствует определению: «конкретный шаг для достижения цели»?","o":["заключение","задача проекта","объект исследования","презентация"],"a":1},{"t":"Какое понятие соответствует определению: «наглядное представление результатов проекта»?","o":["вывод","презентация","риски проекта","аннотация"],"a":1},{"t":"Что такое «методы исследования»?","o":["отзыв с оценкой проектной работы","процесс или явление, которое изучается","способы получения и обработки информации","перечень использованных источников"],"a":2},{"t":"Что такое «ресурсы проекта»?","o":["книга, сайт, человек, дающие сведения по теме","определение действий, сроков и ресурсов проекта","средства, необходимые для выполнения (время, деньги, люди)","метод сбора данных без вмешательства в процесс"],"a":2},{"t":"Какое понятие соответствует определению: «книга, сайт, человек, дающие сведения по теме»?","o":["источник информации","продукт проекта","исследовательский проект","проект"],"a":0},{"t":"Какое понятие соответствует определению: «краткое изложение содержания работы»?","o":["аннотация","актуальность","предмет исследования","презентация"],"a":0}],"short":[{"t":"Как называется недопустимое копирование чужого текста?","a":["плагиат","Плагиат"],"h":"кратко"},{"t":"Назовите понятие по определению: определение действий, сроков и ресурсов проекта","a":["планирование","Планирование"],"h":"термин"},{"t":"Назовите понятие по определению: последовательность стадий: замысел, реализация, защита","a":["этапы проекта","Этапы проекта"],"h":"термин"},{"t":"Назовите понятие по определению: краткое обобщение результатов исследования","a":["вывод","Вывод"],"h":"термин"},{"t":"Назовите понятие по определению: метод соединения частей в единое целое","a":["синтез","Синтез"],"h":"термин"},{"t":"Назовите понятие по определению: метод сбора данных с помощью опроса","a":["анкетирование","Анкетирование"],"h":"термин"},{"t":"Чем завершается работа над проектом?","a":["защитой и выводами","Защитой и выводами"],"h":"кратко"},{"t":"Назовите понятие по определению: часть работы с целью, задачами и актуальностью","a":["введение","Введение"],"h":"термин"},{"t":"Назовите понятие по определению: ограниченная во времени деятельность для создания уникального результата","a":["проект","Проект"],"h":"термин"},{"t":"Назовите понятие по определению: возможные события, мешающие достижению цели","a":["риски проекта","Риски проекта"],"h":"термин"},{"t":"Назовите понятие по определению: публичное представление и обоснование результатов","a":["защита проекта","Защита проекта"],"h":"термин"},{"t":"Назовите понятие по определению: процесс или явление, которое изучается","a":["объект исследования","Объект исследования"],"h":"термин"},{"t":"Назовите понятие по определению: книга, сайт, человек, дающие сведения по теме","a":["источник информации","Источник информации"],"h":"термин"},{"t":"Назовите понятие по определению: средства, необходимые для выполнения (время, деньги, люди)","a":["ресурсы проекта","Ресурсы проекта"],"h":"термин"},{"t":"Назовите понятие по определению: часть работы с выводами по результатам","a":["заключение","Заключение"],"h":"термин"},{"t":"Назовите понятие по определению: способы получения и обработки информации","a":["методы исследования","Методы исследования"],"h":"термин"},{"t":"Назовите понятие по определению: метод изучения путём разбиения целого на части","a":["анализ","Анализ"],"h":"термин"},{"t":"Что из перечисленного — метод исследования?","a":["эксперимент","Эксперимент"],"h":"кратко"},{"t":"Назовите понятие по определению: перечень использованных источников","a":["список литературы","Список литературы"],"h":"термин"},{"t":"Назовите понятие по определению: краткое изложение содержания работы","a":["аннотация","Аннотация"],"h":"термин"},{"t":"Назовите понятие по определению: значимость и востребованность темы проекта","a":["актуальность","Актуальность"],"h":"термин"},{"t":"Назовите понятие по определению: наглядное представление результатов проекта","a":["презентация","Презентация"],"h":"термин"},{"t":"Назовите понятие по определению: метод сбора данных без вмешательства в процесс","a":["наблюдение","Наблюдение"],"h":"термин"},{"t":"Назовите понятие по определению: метод проверки гипотезы в управляемых условиях","a":["эксперимент","Эксперимент"],"h":"термин"},{"t":"Назовите понятие по определению: научное предположение, требующее проверки","a":["гипотеза","Гипотеза"],"h":"термин"}],"match":[{"t":"Соотнесите понятие и определение","L":["эксперимент","гипотеза","задача проекта","наблюдение"],"R":["метод проверки гипотезы в управляемых условиях","научное предположение, требующее проверки","конкретный шаг для достижения цели","метод сбора данных без вмешательства в процесс"],"p":[0,1,2,3]},{"t":"Соотнесите понятие и определение","L":["ресурсы проекта","презентация","анкетирование","гипотеза"],"R":["средства, необходимые для выполнения (время, деньги, люди)","наглядное представление результатов проекта","метод сбора данных с помощью опроса","научное предположение, требующее проверки"],"p":[0,1,2,3]},{"t":"Соотнесите понятие и определение","L":["методы исследования","анкетирование","предмет исследования","аннотация"],"R":["способы получения и обработки информации","метод сбора данных с помощью опроса","конкретная сторона объекта, изучаемая в работе","краткое изложение содержания работы"],"p":[0,1,2,3]},{"t":"Соотнесите понятие и определение","L":["заключение","этапы проекта","предмет исследования","методы исследования"],"R":["часть работы с выводами по результатам","последовательность стадий: замысел, реализация, защита","конкретная сторона объекта, изучаемая в работе","способы получения и обработки информации"],"p":[0,1,2,3]},{"t":"Соотнесите понятие и определение","L":["гипотеза","источник информации","синтез","вывод"],"R":["научное предположение, требующее проверки","книга, сайт, человек, дающие сведения по теме","метод соединения частей в единое целое","краткое обобщение результатов исследования"],"p":[0,1,2,3]},{"t":"Соотнесите понятие и определение","L":["защита проекта","презентация","анкетирование","актуальность"],"R":["публичное представление и обоснование результатов","наглядное представление результатов проекта","метод сбора данных с помощью опроса","значимость и востребованность темы проекта"],"p":[0,1,2,3]},{"t":"Соотнесите понятие и определение","L":["цель проекта","актуальность","список литературы","продукт проекта"],"R":["конечный результат, ради которого выполняется проект","значимость и востребованность темы проекта","перечень использованных источников","материальный или информационный результат работы"],"p":[0,1,2,3]},{"t":"Соотнесите понятие и определение","L":["презентация","список литературы","анализ","эксперимент"],"R":["наглядное представление результатов проекта","перечень использованных источников","метод изучения путём разбиения целого на части","метод проверки гипотезы в управляемых условиях"],"p":[0,1,2,3]},{"t":"Соотнесите понятие и определение","L":["цель проекта","проект","синтез","введение"],"R":["конечный результат, ради которого выполняется проект","ограниченная во времени деятельность для создания уникального результата","метод соединения частей в единое целое","часть работы с целью, задачами и актуальностью"],"p":[0,1,2,3]},{"t":"Соотнесите понятие и определение","L":["защита проекта","этапы проекта","предмет исследования","гипотеза"],"R":["публичное представление и обоснование результатов","последовательность стадий: замысел, реализация, защита","конкретная сторона объекта, изучаемая в работе","научное предположение, требующее проверки"],"p":[0,1,2,3]},{"t":"Соотнесите понятие и определение","L":["аннотация","ресурсы проекта","анализ","задача проекта"],"R":["краткое изложение содержания работы","средства, необходимые для выполнения (время, деньги, люди)","метод изучения путём разбиения целого на части","конкретный шаг для достижения цели"],"p":[0,1,2,3]},{"t":"Соотнесите понятие и определение","L":["риски проекта","практико-ориентированный проект","рецензия","заключение"],"R":["возможные события, мешающие достижению цели","проект с конкретным прикладным продуктом","отзыв с оценкой проектной работы","часть работы с выводами по результатам"],"p":[0,1,2,3]},{"t":"Соотнесите понятие и определение","L":["введение","эксперимент","источник информации","объект исследования"],"R":["часть работы с целью, задачами и актуальностью","метод проверки гипотезы в управляемых условиях","книга, сайт, человек, дающие сведения по теме","процесс или явление, которое изучается"],"p":[0,1,2,3]},{"t":"Соотнесите понятие и определение","L":["список литературы","источник информации","предмет исследования","актуальность"],"R":["перечень использованных источников","книга, сайт, человек, дающие сведения по теме","конкретная сторона объекта, изучаемая в работе","значимость и востребованность темы проекта"],"p":[0,1,2,3]},{"t":"Соотнесите понятие и определение","L":["наблюдение","этапы проекта","аннотация","продукт проекта"],"R":["метод сбора данных без вмешательства в процесс","последовательность стадий: замысел, реализация, защита","краткое изложение содержания работы","материальный или информационный результат работы"],"p":[0,1,2,3]}]}